json_streams/__init__.py
json_streams/_types.py
json_streams/py.typed
json_streams-0.14.0.dist-info/METADATA
json_streams-0.14.0.dist-info/WHEEL
json_streams-0.14.0.dist-info/RECORD
